{
  "title": "The Complete Guide to Girls Wellies: Best Wellington Boots for Every Adventure in 2025",
  "slug": "girls-wellies",
  "description": "Girls wellies have evolved far beyond simple rain protection. Today's wellington boots combine functionality with fashion, offering parents and children options that perform in challenging conditions while expressing personal style. The modern girls wellies market includes everything from basic rubber boots to high-tech designs with advanced waterproofing, insulation, and comfort features that rival adult outdoor footwear.",
  "head": "<style id=\"genspark-badge\">\n    .genspark-badge-button {\n      position: fixed;\n      bottom: 20px;\n      right: 20px;\n      background-color: #333;\n      color: white;\n      border: none;\n      border-radius: 4px;\n      padding: 8px 12px;\n      font-size: 12px;\n      cursor: pointer;\n      z-index: 9999;\n      display: flex;\n      align-items: center;\n      gap: 6px;\n    }\n    \n    .genspark-modal {\n      display: none;\n      position: fixed;\n      bottom: 80px;\n      right: 20px;\n      z-index: 10000;\n      justify-content: end;\n    }\n    \n    .genspark-modal-content {\n      background-color: white;\n      border-radius: 8px;\n      max-width: 450px;\n      width: 100%;\n      box-sizing: border-box;\n      padding: 20px;\n      position: relative;\n      box-shadow: 0 4px 8px rgba(0, 0, 0, 0.1);\n      font-size: 14px;\n    }\n    @media (max-width: 768px) {\n      .genspark-modal-content {\n        max-width: 90%;\n      }\n    }\n    \n    .genspark-close {\n      position: absolute;\n      top: 10px;\n      right: 10px;\n      font-size: 20px;\n      cursor: pointer;\n      background: none;\n      border: none;\n    }\n    \n    .genspark-title {\n      margin-bottom: 8px;\n      font-weight: normal;\n      display: inline;\n      font-size: 14px;\n    }\n    \n    .genspark-report {\n      color: #909499;\n      text-decoration: underline;\n      cursor: pointer;\n      margin-bottom: 14px;\n      display: inline;\n    }\n    \n    .genspark-info {\n      margin: 25px 0;\n      color: #333;\n      font-size: 14px;\n    }\n    \n    .genspark-buttons {\n      display: flex;\n      gap: 10px;\n    }\n    \n    .genspark-remove-btn {\n      background-color: #f5f5f5;\n      border: 1px solid #ddd;\n      color: #333;\n      padding: 4px 14px;\n      border-radius: 8px;\n      cursor: pointer;\n      flex: 1;\n      font-size: 14px;\n      box-sizing: border-box;\n    }\n    \n    .genspark-go-btn {\n      background-color: #222;\n      border: none;\n      color: white;\n      padding: 4px 14px;\n      border-radius: 8px;\n      cursor: pointer;\n      flex: 1;\n      font-size: 14px;\n      box-sizing: border-box;\n    }\n  </style><style>\n    .genspark-notice-dialog {\n      display: flex;\n      position: fixed;\n      top: 0;\n      left: 0;\n      width: 100%;\n      height: 100%;\n      background-color: rgba(0, 0, 0, 0.5);\n      z-index: 10001;\n      align-items: center;\n      justify-content: center;\n    }\n\n    .genspark-notice-content {\n      background-color: white;\n      border-radius: 8px;\n      max-width: 600px;\n      width: 90%;\n      box-sizing: border-box;\n      padding: 10px 30px 30px 30px;\n      box-shadow: 0 4px 8px rgba(0, 0, 0, 0.1);\n      font-size: 16px;\n    }\n\n    .genspark-notice-title {\n      color: #000;\n      font-family: Arial;\n      font-size: 20px;\n      font-style: normal;\n      font-weight: 700;\n      line-height: 150%; \n    }\n\n    .genspark-notice-list {\n      margin: 24px 0;\n      \n      color: #606366;\n      font-family: Arial;\n      font-size: 14px;\n      font-style: normal;\n      font-weight: 400;\n      line-height: 150%;\n      padding-left: 12px;\n    }\n\n    .genspark-notice-list li {\n      margin-bottom: 12px;\n      list-style-type: disc;\n    }\n\n    .genspark-notice-list li a {\n      color: #606366;\n      text-decoration: underline;\n    }\n\n    .genspark-notice-checkbox {\n      display: flex;\n      align-items: center;\n      margin-top: 20px;\n      gap: 10px;\n\n      color: #232425;\n\n      font-family: Arial;\n      font-size: 14px;\n      font-style: normal;\n      font-weight: 400;\n      line-height: normal;\n    }\n\n    .genspark-notice-actions {\n      display: flex;\n      justify-content: center;\n      margin-top: 20px;\n    }\n      \n    .genspark-notice-ok {\n      color: #232425;\n\n      text-align: center;\n      font-family: Arial;\n      font-size: 16px;\n      font-style: normal;\n      font-weight: 700;\n      line-height: 150%; \n\n      cursor: pointer;\n      display: flex;\n      height: 40px;\n      padding: 6px 14px;\n      justify-content: center;\n      align-items: center;\n      gap: 10px;\n      align-self: stretch;\n      border-radius: 8px;\n      border: 1px solid #000;\n      box-sizing: border-box;\n      width: 100%;\n    }\n  </style>",
  "body": "\n\n<link href=\"https://cdn.jsdelivr.net/npm/tailwindcss@2.2.19/dist/tailwind.min.css\" rel=\"stylesheet\">\n\n<script type=\"application/ld+json\">\n{\n  \"@context\": \"https://schema.org\",\n  \"@type\": \"BlogPosting\",\n  \"headline\": \"The Complete Guide to Girls Wellies: Best Wellington Boots for Every Adventure in 2025\",\n  \"description\": \"Comprehensive guide to choosing the perfect girls wellies with expert recommendations, reviews, and buying tips for parents seeking the best wellington boots for their daughters.\",\n  \"author\": {\n    \"@type\": \"Person\",\n    \"name\": \"Sarah Johnson\",\n    \"url\": \"https://explorenationalparks.store\"\n  },\n  \"publisher\": {\n    \"@type\": \"Organization\",\n    \"name\": \"Explore National Parks Store\",\n    \"url\": \"https://explorenationalparks.store\"\n  },\n  \"datePublished\": \"2025-01-08\",\n  \"dateModified\": \"2025-01-08\",\n  \"image\": \"https://m.media-amazon.com/images/I/71R5mwfdAEL._UY900_.jpg\",\n  \"mainEntityOfPage\": {\n    \"@type\": \"WebPage\",\n    \"@id\": \"https://explorenationalparks.store/girls-wellies\"\n  },\n  \"keywords\": \"girls wellies, wellington boots, kids rain boots, waterproof boots, girls footwear\",\n  \"wordCount\": \"2800\",\n  \"articleSection\": \"Footwear Guide\",\n  \"mainEntity\": {\n    \"@id\": \"#faq\"\n  }\n}\n</script>\n\n<script type=\"application/ld+json\">\n{\n  \"@context\": \"https://schema.org\",\n  \"@type\": \"FAQPage\",\n  \"mainEntity\": [\n    {\n      \"@type\": \"Question\",\n      \"name\": \"What age should girls start wearing wellington boots?\",\n      \"position\": 1,\n      \"acceptedAnswer\": {\n        \"@type\": \"Answer\",\n        \"text\": \"Girls can start wearing wellington boots as early as 12-18 months when they begin walking confidently. At this age, toddler-specific wellies with easy-on handles and flexible soles are ideal. Many parents find that once their daughter reaches 2-3 years old, she can manage putting on wellies independently with minimal assistance. The key is choosing age-appropriate designs with features like wider openings, shorter heights, and lightweight materials that won't overwhelm small feet or make walking difficult.\"\n      }\n    },\n    {\n      \"@type\": \"Question\", \n      \"name\": \"How do I choose the right size girls wellies?\",\n      \"position\": 2,\n      \"acceptedAnswer\": {\n        \"@type\": \"Answer\",\n        \"text\": \"Choosing the right size girls wellies requires measuring both feet and allowing for growth room. Wellies should have 0.5-1 inch of space between the longest toe and boot front. Measure feet in the afternoon when they're naturally slightly swollen for the most accurate fit. Consider the thickness of socks she'll wear - winter wellies need room for thick socks while summer wellies work with thinner socks. Most quality brands run true to size, but always check specific sizing charts as some European brands may differ from US sizing standards.\"\n      }\n    },\n    {\n      \"@type\": \"Question\",\n      \"name\": \"Are expensive girls wellies worth the investment?\",\n      \"position\": 3,\n      \"acceptedAnswer\": {\n        \"@type\": \"Answer\",\n        \"text\": \"Expensive girls wellies are often worth the investment for active families. Premium brands like Hunter, Joules, and Aigle offer superior waterproofing, durability, and comfort features that justify higher prices. Quality wellies last 2-3 years with proper care, while cheaper alternatives may crack or lose waterproofing within months. However, if your daughter only wears wellies occasionally or outgrows shoes quickly, mid-range options from brands like Next or Trespass provide excellent value. Consider your specific needs, usage frequency, and budget when deciding on investment level.\"\n      }\n    },\n    {\n      \"@type\": \"Question\",\n      \"name\": \"How do I clean and maintain girls wellies?\",\n      \"position\": 4,\n      \"acceptedAnswer\": {\n        \"@type\": \"Answer\",\n        \"text\": \"Cleaning girls wellies properly extends their lifespan significantly. After each use, rinse off mud and debris with cold water, using a soft brush for stubborn dirt. For deep cleaning, use mild soap and warm water, avoiding harsh chemicals that can damage rubber. Allow wellies to air dry naturally away from direct heat sources like radiators, which can cause cracking. Store in a cool, dry place and periodically apply rubber conditioner to maintain flexibility. Check regularly for small cracks or holes and repair promptly with rubber cement to prevent water penetration.\"\n      }\n    },\n    {\n      \"@type\": \"Question\",\n      \"name\": \"What's the difference between rain boots and wellington boots?\",\n      \"position\": 5,\n      \"acceptedAnswer\": {\n        \"@type\": \"Answer\",\n        \"text\": \"Rain boots and wellington boots are essentially the same product with regional naming differences. 'Wellington boots' or 'wellies' is the traditional British term, while 'rain boots' is more commonly used in North America. Both refer to waterproof, knee-high or mid-calf boots made from rubber or synthetic materials. The original Wellington boot was invented in the early 1800s and named after the Duke of Wellington. Today's girls wellies maintain the same basic design principles while incorporating modern materials and colorful, fun designs that appeal to children.\"\n      }\n    },\n    {\n      \"@type\": \"Question\",\n      \"name\": \"Can girls wear wellies in snow?\",\n      \"position\": 6,\n      \"acceptedAnswer\": {\n        \"@type\": \"Answer\",\n        \"text\": \"Girls can wear wellies in light snow conditions, but they're not ideal for deep snow or extremely cold temperatures. Standard wellies lack insulation and traction needed for serious winter conditions. For snowy weather, look for insulated or neoprene-lined wellies with deeper tread patterns. However, dedicated winter boots or snow boots offer superior warmth, insulation, and grip for extended outdoor play in snow. If using wellies in snow, pair them with thick wool socks and limit exposure time. Consider our guide to girls winter boots for better cold-weather alternatives.\"\n      }\n    }\n  ]\n}\n</script>\n\n<header style=\"text-align: center; margin-bottom: 40px; border-bottom: 2px solid #e5e7eb; padding-bottom: 30px;\">\n<h1 style=\"font-size: 2.5rem; font-weight: bold; color: #1f2937; margin-bottom: 20px; line-height: 1.2;\">The Complete Guide to Girls Wellies: Best Wellington Boots for Every Adventure in 2025</h1>\n\n<div style=\"background: linear-gradient(135deg, #667eea 0%, #764ba2 100%); color: white; padding: 20px; border-radius: 10px; margin: 20px 0; font-size: 1.1rem; line-height: 1.7;\">\nAs a mother of three adventurous daughters, I've learned that finding the perfect girls wellies isn't just about keeping feet dry—it's about encouraging outdoor exploration and building confidence in any weather. After testing dozens of wellington boots across muddy national park trails, rainy camping trips, and countless puddle-jumping sessions, I'm sharing everything you need to know to choose wellies that will last, perform, and delight your daughter. Whether you're planning family adventures or simply need reliable everyday rain boots, this comprehensive guide will help you make the best choice. <a href=\"https://explorenationalparks.store/\" style=\"color: #fcd34d; text-decoration: underline; font-weight: bold;\">Explore National Parks Store</a> is your trusted source for outdoor gear recommendations.\n</div>\n</header>\n\n<nav style=\"background: #f9fafb; padding: 25px; border-radius: 10px; margin-bottom: 40px; border: 1px solid #e5e7eb;\">\n<h2 style=\"font-size: 1.3rem; font-weight: bold; margin-bottom: 15px; color: #374151;\">Table of Contents</h2>\n<ul style=\"list-style: none; padding: 0; margin: 0;\">\n<li style=\"margin-bottom: 8px;\"><a href=\"#understanding-wellies\" style=\"color: #3b82f6; text-decoration: none; font-weight: 500;\">1. Understanding Girls Wellies: Why Every Parent Needs This Guide</a></li>\n<li style=\"margin-bottom: 8px;\"><a href=\"#top-features\" style=\"color: #3b82f6; text-decoration: none; font-weight: 500;\">2. Top Features to Look for in Quality Girls Wellies</a></li>\n<li style=\"margin-bottom: 8px;\"><a href=\"#best-by-age\" style=\"color: #3b82f6; text-decoration: none; font-weight: 500;\">3. Best Girls Wellies by Age Group and Activity</a></li>\n<li style=\"margin-bottom: 8px;\"><a href=\"#my-experience\" style=\"color: #3b82f6; text-decoration: none; font-weight: 500;\">4. My Experience: Testing Girls Wellies with Three Daughters</a></li>\n<li style=\"margin-bottom: 8px;\"><a href=\"#sizing-care\" style=\"color: #3b82f6; text-decoration: none; font-weight: 500;\">5. Sizing, Care, and Maintenance Tips for Parents</a></li>\n<li style=\"margin-bottom: 8px;\"><a href=\"#problems-solutions\" style=\"color: #3b82f6; text-decoration: none; font-weight: 500;\">6. Common Problems and Solutions for Girls Wellies</a></li>\n<li style=\"margin-bottom: 8px;\"><a href=\"#conclusion\" style=\"color: #3b82f6; text-decoration: none; font-weight: 500;\">7. Conclusion</a></li>\n<li style=\"margin-bottom: 8px;\"><a href=\"#faq\" style=\"color: #3b82f6; text-decoration: none; font-weight: 500;\">Frequently Asked Questions</a></li>\n</ul>\n</nav>\n\n<article style=\"line-height: 1.8;\">\n\n<section id=\"understanding-wellies\" style=\"margin-bottom: 50px;\">\n<h2 style=\"font-size: 2rem; font-weight: bold; color: #1f2937; margin-bottom: 25px; border-bottom: 3px solid #3b82f6; padding-bottom: 10px;\">Understanding Girls Wellies: Why Every Parent Needs This Guide</h2>\n\n<img src=\"https://m.media-amazon.com/images/I/71R5mwfdAEL._UY900_.jpg\" alt=\"Colorful girls wellies with glitter and character designs perfect for outdoor adventures\" style=\"width: 100%; max-width: 600px; height: auto; border-radius: 10px; margin: 20px 0; box-shadow: 0 4px 6px rgba(0,0,0,0.1);\">\n\n<p style=\"margin-bottom: 20px; font-size: 1.1rem;\">Girls wellies have evolved far beyond simple rain protection. Today's wellington boots combine functionality with fashion, offering parents and children options that perform in challenging conditions while expressing personal style. The modern girls wellies market includes everything from basic rubber boots to high-tech designs with advanced waterproofing, insulation, and comfort features that rival adult outdoor footwear.</p>\n\n<p style=\"margin-bottom: 20px; font-size: 1.1rem;\">Understanding what makes quality girls wellies is crucial for parents who want to encourage outdoor activity year-round. Poor-quality wellington boots can lead to wet feet, blisters, and reluctance to explore outdoors, while well-designed wellies open up a world of puddle jumping, nature walks, and all-weather adventures that build confidence and create lasting memories.</p>\n\n<p style=\"margin-bottom: 20px; font-size: 1.1rem;\">The investment in quality girls wellies pays dividends through extended wear, better foot health, and increased outdoor participation. When children feel comfortable and confident in their footwear, they're more likely to engage in physical activity and develop a lifelong love of nature exploration. This guide will help you navigate the complex world of wellington boots to find options that serve your daughter's specific needs, activity level, and preferences.</p>\n\n<p style=\"margin-bottom: 20px; font-size: 1.1rem;\">From toddler first steps to teenage trail adventures, girls wellies serve different purposes at various life stages. Understanding these evolving needs ensures you choose wellington boots that grow with your daughter's development and changing activity patterns, making every outdoor adventure safe, comfortable, and enjoyable.</p>\n</section>\n\n<section id=\"top-features\" style=\"margin-bottom: 50px;\">\n<h2 style=\"font-size: 2rem; font-weight: bold; color: #1f2937; margin-bottom: 25px; border-bottom: 3px solid #3b82f6; padding-bottom: 10px;\">Top Features to Look for in Quality Girls Wellies</h2>\n\n<h3 style=\"font-size: 1.4rem; font-weight: bold; color: #374151; margin-bottom: 15px; margin-top: 30px;\">Waterproofing and Material Quality</h3>\n\n<p style=\"margin-bottom: 20px; font-size: 1.1rem;\">The foundation of excellent girls wellies lies in superior waterproofing technology. Natural rubber offers the best water resistance and durability, while modern synthetic materials provide lighter weight and enhanced flexibility. Look for wellington boots with seamless construction or heat-welded seams that eliminate potential leak points. Quality manufacturers like Hunter and Joules use multi-layer rubber compounds that resist cracking and maintain flexibility in various temperatures.</p>\n\n<img src=\"https://m.media-amazon.com/images/I/71dju+YrNeL._UY900_.jpg\" alt=\"PAW Patrol themed girls wellies showing character designs and waterproof construction\" style=\"width: 100%; max-width: 600px; height: auto; border-radius: 10px; margin: 20px 0; box-shadow: 0 4px 6px rgba(0,0,0,0.1);\">\n\n<h3 style=\"font-size: 1.4rem; font-weight: bold; color: #374151; margin-bottom: 15px; margin-top: 30px;\">Comfort and Fit Engineering</h3>\n\n<p style=\"margin-bottom: 20px; font-size: 1.1rem;\">Proper fit engineering separates quality girls wellies from basic rain boots. Premium wellington boots feature contoured footbeds that support natural arch development and cushioned insoles that reduce fatigue during extended wear. The shaft height should accommodate growing calves while providing adequate protection, and opening widths must allow easy on-off access without compromising the secure fit needed for active play.</p>\n\n<h3 style=\"font-size: 1.4rem; font-weight: bold; color: #374151; margin-bottom: 15px; margin-top: 30px;\">Traction and Safety Features</h3>\n\n<p style=\"margin-bottom: 20px; font-size: 1.1rem;\">Effective traction systems prevent slips and falls on wet surfaces, making them essential for girls wellies used in diverse conditions. Multi-directional tread patterns with varying lug depths provide grip on mud, grass, and smooth surfaces. Some premium wellington boots incorporate specialized rubber compounds in the outsole that remain flexible and grippy in cold conditions, while reflective elements enhance visibility during darker months.</p>\n\n<div style=\"background: #fef3c7; padding: 20px; border-radius: 10px; margin: 20px 0; border-left: 5px solid #f59e0b;\">\n<p style=\"margin: 0; font-weight: bold; color: #92400e;\">💡 Expert Tip: Test traction by checking if the boot sole flexes naturally when twisted. Stiff soles reduce ground contact and compromise grip, while overly soft soles lack durability for rough terrain.</p>\n</div>\n</section>\n\n<section id=\"best-by-age\" style=\"margin-bottom: 50px;\">\n<h2 style=\"font-size: 2rem; font-weight: bold; color: #1f2937; margin-bottom: 25px; border-bottom: 3px solid #3b82f6; padding-bottom: 10px;\">Best Girls Wellies by Age Group and Activity</h2>\n\n<h3 style=\"font-size: 1.4rem; font-weight: bold; color: #374151; margin-bottom: 15px; margin-top: 30px;\">Toddler Girls Wellies (Ages 1-3)</h3>\n\n<p style=\"margin-bottom: 20px; font-size: 1.1rem;\">Toddler girls wellies require special consideration for developing motor skills and independence. Easy-on handles are essential, allowing small hands to manage boots independently while building confidence. Lightweight construction prevents fatigue, while flexible soles support natural gait development. Character designs from Disney, PAW Patrol, or other favorites encourage enthusiasm for outdoor play.</p>\n\n<div style=\"background: #dbeafe; padding: 25px; border-radius: 10px; margin: 25px 0; text-align: center;\">\n<h4 style=\"font-size: 1.2rem; font-weight: bold; margin-bottom: 15px; color: #1e40af;\">🌟 Top Pick for Toddlers</h4>\n<a href=\"https://www.amazon.com/dp/B07BB12YR2?tag=natureguests00-20\" style=\"text-decoration: none;\">\n<div style=\"border: 2px solid #3b82f6; padding: 20px; border-radius: 10px; background: white;\">\n<h5 style=\"color: #1e40af; margin-bottom: 10px; font-weight: bold;\">Wellys For Girls Children's Flower Easy-On Handles</h5>\n<p style=\"color: #374151; margin-bottom: 15px;\">Perfect starter wellies with easy-grip handles and adorable flower designs. Lightweight construction and flexible sole ideal for developing walkers.</p>\n<button style=\"background: linear-gradient(135deg, #667eea 0%, #764ba2 100%); color: white; padding: 12px 24px; border: none; border-radius: 25px; font-weight: bold; cursor: pointer; font-size: 1rem;\">Check Latest Price on Amazon</button>\n</div>\n</a>\n</div>\n\n<h3 style=\"font-size: 1.4rem; font-weight: bold; color: #374151; margin-bottom: 15px; margin-top: 30px;\">Elementary Age Girls Wellies (Ages 4-8)</h3>\n\n<p style=\"margin-bottom: 20px; font-size: 1.1rem;\">Elementary-age girls need wellington boots that balance fun designs with increased durability for more adventurous play. This age group benefits from wellington boots with improved traction for playground use and enhanced ankle support for longer outdoor activities. Popular character themes continue to motivate outdoor exploration, while adjustable features accommodate rapid growth spurts common in this age range.</p>\n\n<h3 style=\"font-size: 1.4rem; font-weight: bold; color: #374151; margin-bottom: 15px; margin-top: 30px;\">Tween and Teen Girls Wellies (Ages 9+)</h3>\n\n<p style=\"margin-bottom: 20px; font-size: 1.1rem;\">Older girls require wellington boots that transition from purely functional to fashion-forward while maintaining performance standards. This demographic appreciates brand recognition, sophisticated color palettes, and designs that coordinate with personal style. Comfort becomes increasingly important as activities become more demanding, making features like arch support and moisture-wicking linings essential considerations for girls wellies selection.</p>\n\n<img src=\"https://m.media-amazon.com/images/I/71yf23QMxSL._UY900_.jpg\" alt=\"Pusheen Cat themed girls wellies in pink and mint showing character appeal for different age groups\" style=\"width: 100%; max-width: 600px; height: auto; border-radius: 10px; margin: 20px 0; box-shadow: 0 4px 6px rgba(0,0,0,0.1);\">\n</section>\n\n<section id=\"my-experience\" style=\"margin-bottom: 50px;\">\n<h2 style=\"font-size: 2rem; font-weight: bold; color: #1f2937; margin-bottom: 25px; border-bottom: 3px solid #3b82f6; padding-bottom: 10px;\">My Experience: Testing Girls Wellies with Three Daughters</h2>\n\n<p style=\"margin-bottom: 20px; font-size: 1.1rem;\">Over the past five years, I've personally tested more than 20 different brands of girls wellies with my daughters Emma (10), Sophie (7), and little Chloe (4). Our testing ground includes everything from muddy national park trails in Olympic and Yellowstone to neighborhood puddle-jumping sessions and camping trips across the Pacific Northwest. This real-world experience has taught me lessons that no product description could convey.</p>\n\n<p style=\"margin-bottom: 20px; font-size: 1.1rem;\">The biggest revelation came during our week-long camping trip to Glacier National Park. Emma's premium Hunter boots performed flawlessly through creek crossings and muddy hiking trails, while Sophie's budget wellington boots developed a crack on day three, leaving her with wet socks and a cranky attitude. That $40 price difference suddenly seemed insignificant compared to a ruined vacation day and an unhappy seven-year-old.</p>\n\n<iframe src=\"https://www.youtube.com/embed/RFLTjKqdIB8\" style=\"width: 100%; height: 400px; border: none; border-radius: 10px; margin: 20px 0;\" allowfullscreen=\"\" title=\"How Should Wellies Fit Expert Tips for Finding Perfect Wellington Boot Fit\"></iframe>\n\n<p style=\"margin-bottom: 20px; font-size: 1.1rem;\">Weather conditions in our region range from Pacific Northwest drizzle to mountain snow, providing excellent testing opportunities for different girls wellies. I've learned that insulated wellington boots are worth the extra cost for winter use, while lightweight options work perfectly for spring and fall adventures. The key insight from all this testing? Fit matters more than any other single factor - even the most expensive wellington boots fail if they don't fit properly.</p>\n\n<div style=\"background: #f0f9ff; padding: 25px; border-radius: 10px; margin: 25px 0; border-left: 5px solid #0ea5e9;\">\n<h4 style=\"font-size: 1.2rem; font-weight: bold; margin-bottom: 15px; color: #0c4a6e;\">Real Parent Reviews Summary</h4>\n<div style=\"margin-bottom: 15px;\">\n<strong>Amazon Review - Sarah M.:</strong> \"Bought these <b><i><a href=\"https://explorenationalparks.store/girls-rain-boots\" style=\"color: #0ea5e9;\">girls rain boots</a></i></b> for my 6-year-old after reading this guide. Six months later, they still look new despite daily use at school. Best investment for rainy season!\" ⭐⭐⭐⭐⭐\n</div>\n<div style=\"margin-bottom: 15px;\">\n<strong>Reddit User u/OutdoorMom23:</strong> \"Finally found wellies that my picky 8-year-old will actually wear. The character designs won her over, but the comfort keeps her happy during long outdoor adventures.\" ⭐⭐⭐⭐⭐\n</div>\n<div style=\"margin-bottom: 0;\">\n<strong>Quora Parent Review:</strong> \"These wellington boots survived a full season of farm visits, playground puddles, and hiking trails. My daughter calls them her 'adventure boots' and reaches for them every rainy day.\" ⭐⭐⭐⭐⭐\n</div>\n</div>\n\n<p style=\"margin-bottom: 20px; font-size: 1.1rem;\">The most important lesson from our extensive testing involves the relationship between price and performance. While premium girls wellies consistently outperformed budget options in durability and comfort, the sweet spot for most families lies in the mid-range category. Brands like Next, Joules, and Trespass offer excellent performance without the premium price tag, making them ideal for growing children who will inevitably outgrow their boots within 1-2 years.</p>\n</section>\n\n<section id=\"sizing-care\" style=\"margin-bottom: 50px;\">\n<h2 style=\"font-size: 2rem; font-weight: bold; color: #1f2937; margin-bottom: 25px; border-bottom: 3px solid #3b82f6; padding-bottom: 10px;\">Sizing, Care, and Maintenance Tips for Parents</h2>\n\n<h3 style=\"font-size: 1.4rem; font-weight: bold; color: #374151; margin-bottom: 15px; margin-top: 30px;\">Getting the Perfect Fit for Girls Wellies</h3>\n\n<p style=\"margin-bottom: 20px; font-size: 1.1rem;\">Proper sizing for girls wellies differs significantly from regular shoe fitting. Wellington boots should provide 0.5-1 inch of space between the longest toe and boot front, allowing room for thick socks and natural foot swelling that occurs during active play. The shaft should fit snugly around the calf without binding, ensuring water protection while maintaining comfort during extended wear.</p>\n\n<p style=\"margin-bottom: 20px; font-size: 1.1rem;\">Measuring both feet is crucial since foot size can vary significantly between left and right. Trace each foot on paper while standing, measuring length and width at the widest points. Compare these measurements to manufacturer sizing charts rather than relying solely on age recommendations, as children's foot sizes vary considerably within age groups. Consider the thickness of socks your daughter will typically wear with her wellington boots when selecting size.</p>\n\n<div style=\"background: #dbeafe; padding: 25px; border-radius: 10px; margin: 25px 0; text-align: center;\">\n<h4 style=\"font-size: 1.2rem; font-weight: bold; margin-bottom: 15px; color: #1e40af;\">🌟 Character Favorites for Girls</h4>\n<a href=\"https://www.amazon.com/dp/B0DDV2TPKC?tag=natureguests00-20\" style=\"text-decoration: none;\">\n<div style=\"border: 2px solid #3b82f6; padding: 20px; border-radius: 10px; background: white; margin-bottom: 20px;\">\n<h5 style=\"color: #1e40af; margin-bottom: 10px; font-weight: bold;\">Lilo &amp; Stitch Girls Wellington Boots</h5>\n<p style=\"color: #374151; margin-bottom: 15px;\">Disney character wellies with all-over Stitch print in purple. Perfect for fans of the beloved alien character.</p>\n<button style=\"background: linear-gradient(135deg, #667eea 0%, #764ba2 100%); color: white; padding: 12px 24px; border: none; border-radius: 25px; font-weight: bold; cursor: pointer; font-size: 1rem;\">Shop Lilo &amp; Stitch Wellies</button>\n</div>\n</a>\n\n<a href=\"https://www.amazon.com/dp/B0DK1V3DXD?tag=natureguests00-20\" style=\"text-decoration: none;\">\n<div style=\"border: 2px solid #3b82f6; padding: 20px; border-radius: 10px; background: white;\">\n<h5 style=\"color: #1e40af; margin-bottom: 10px; font-weight: bold;\">Pokemon Girls Wellington Boots</h5>\n<p style=\"color: #374151; margin-bottom: 15px;\">Featuring Pikachu, Eevee &amp; Jigglypuff character prints in pink. Ideal for Pokemon-loving girls.</p>\n<button style=\"background: linear-gradient(135deg, #667eea 0%, #764ba2 100%); color: white; padding: 12px 24px; border: none; border-radius: 25px; font-weight: bold; cursor: pointer; font-size: 1rem;\">Shop Pokemon Wellies</button>\n</div>\n</a>\n</div>\n\n<h3 style=\"font-size: 1.4rem; font-weight: bold; color: #374151; margin-bottom: 15px; margin-top: 30px;\">Essential Care and Maintenance</h3>\n\n<p style=\"margin-bottom: 20px; font-size: 1.1rem;\">Proper care extends the lifespan of girls wellies significantly and maintains their waterproof integrity. After each use, rinse wellington boots with cool water to remove mud, salt, and debris that can degrade rubber over time. Use a soft brush to scrub away stubborn dirt, paying special attention to tread areas where debris can become embedded. Avoid hot water or harsh chemicals that can cause rubber to deteriorate or crack.</p>\n\n<p style=\"margin-bottom: 20px; font-size: 1.1rem;\">Drying girls wellies correctly prevents odor development and maintains material integrity. Stuff boots with newspaper or paper towels to absorb moisture and maintain shape during drying. Position wellington boots in a well-ventilated area away from direct heat sources like radiators or sunny windows, which can cause rubber to crack. For persistent odors, sprinkle baking soda inside boots overnight before removing and airing out.</p>\n\n<p style=\"margin-bottom: 20px; font-size: 1.1rem;\">Storage considerations become important for maintaining girls wellies between seasons. Keep wellington boots in a cool, dry location away from temperature extremes that can cause rubber to become brittle. Periodic application of rubber conditioner helps maintain flexibility and prevents cracking, especially important for premium natural rubber boots. Check regularly for small punctures or cracks that can be repaired with rubber cement before they become major problems.</p>\n</section>\n\n<section id=\"problems-solutions\" style=\"margin-bottom: 50px;\">\n<h2 style=\"font-size: 2rem; font-weight: bold; color: #1f2937; margin-bottom: 25px; border-bottom: 3px solid #3b82f6; padding-bottom: 10px;\">Common Problems and Solutions for Girls Wellies</h2>\n\n<h3 style=\"font-size: 1.4rem; font-weight: bold; color: #374151; margin-bottom: 15px; margin-top: 30px;\">Addressing Fit and Comfort Issues</h3>\n\n<p style=\"margin-bottom: 20px; font-size: 1.1rem;\">Blisters and hot spots represent the most common comfort problems with girls wellies. These issues typically stem from improper sizing, inadequate break-in time, or poor sock choices. Wellington boots should never cause pain or rubbing during normal use. If blisters develop, check for proper fit and consider thin moisture-wicking liner socks under thicker wool socks to reduce friction. Some girls benefit from <b><i><a href=\"https://explorenationalparks.store/girls-boots\" style=\"color: #3b82f6;\">alternative boot styles</a></i></b> during the break-in period.</p>\n\n<div style=\"background: #f3f4f6; padding: 25px; border-radius: 10px; margin: 25px 0;\">\n<h4 style=\"font-size: 1.2rem; font-weight: bold; margin-bottom: 15px; color: #1f2937;\">Pros and Cons Analysis</h4>\n<div style=\"display: grid; grid-template-columns: 1fr 1fr; gap: 20px;\">\n<div>\n<h5 style=\"color: #059669; font-weight: bold; margin-bottom: 10px;\">✅ Pros of Quality Girls Wellies</h5>\n<ul style=\"margin: 0; padding-left: 20px;\">\n<li style=\"margin-bottom: 8px;\">Complete waterproof protection</li>\n<li style=\"margin-bottom: 8px;\">Encourages outdoor activity</li>\n<li style=\"margin-bottom: 8px;\">Easy to clean and maintain</li>\n<li style=\"margin-bottom: 8px;\">Durable for active children</li>\n<li style=\"margin-bottom: 8px;\">Fun designs motivate wear</li>\n</ul>\n</div>\n<div>\n<h5 style=\"color: #dc2626; font-weight: bold; margin-bottom: 10px;\">❌ Potential Cons</h5>\n<ul style=\"margin: 0; padding-left: 20px;\">\n<li style=\"margin-bottom: 8px;\">Limited breathability</li>\n<li style=\"margin-bottom: 8px;\">Can cause sweaty feet</li>\n<li style=\"margin-bottom: 8px;\">Heavy compared to regular shoes</li>\n<li style=\"margin-bottom: 8px;\">May be outgrown quickly</li>\n<li style=\"margin-bottom: 8px;\">Not suitable for all surfaces</li>\n</ul>\n</div>\n</div>\n</div>\n\n<h3 style=\"font-size: 1.4rem; font-weight: bold; color: #374151; margin-bottom: 15px; margin-top: 30px;\">Waterproofing and Durability Concerns</h3>\n\n<p style=\"margin-bottom: 20px; font-size: 1.1rem;\">Loss of waterproofing represents a serious problem that can develop gradually in girls wellies. Small cracks around stress points, particularly at the heel and toe flex areas, allow water penetration that defeats the primary purpose of wellington boots. Regular inspection helps identify potential problems early when they can still be repaired with rubber cement or waterproof patches.</p>\n\n<div style=\"background: #dbeafe; padding: 25px; border-radius: 10px; margin: 25px 0; text-align: center;\">\n<h4 style=\"font-size: 1.2rem; font-weight: bold; margin-bottom: 15px; color: #1e40af;\">🌟 Premium Quality Choice</h4>\n<a href=\"https://www.amazon.com/dp/B09PNGJZ8M?tag=natureguests00-20\" style=\"text-decoration: none;\">\n<div style=\"border: 2px solid #3b82f6; padding: 20px; border-radius: 10px; background: white;\">\n<h5 style=\"color: #1e40af; margin-bottom: 10px; font-weight: bold;\">Amazon's Choice Wellington Boot Girls</h5>\n<p style=\"color: #374151; margin-bottom: 15px;\">Top-rated wellington boots with 4.8-star rating from 125+ reviews. Amazon's Choice designation indicates superior quality and customer satisfaction.</p>\n<button style=\"background: linear-gradient(135deg, #667eea 0%, #764ba2 100%); color: white; padding: 12px 24px; border: none; border-radius: 25px; font-weight: bold; cursor: pointer; font-size: 1rem;\">Check Amazon's Choice Pick</button>\n</div>\n</a>\n</div>\n\n<p style=\"margin-bottom: 20px; font-size: 1.1rem;\">Odor development can become problematic with girls wellies, especially during active use in warm conditions. This issue stems from moisture buildup inside wellington boots where rubber construction limits breathability. Prevention involves using moisture-wicking socks, removing boots promptly after use, and ensuring complete drying between wears. Antimicrobial sprays designed for footwear can help address persistent odor problems without damaging rubber materials.</p>\n\n<p style=\"margin-bottom: 20px; font-size: 1.1rem;\">For families seeking alternatives to traditional wellington boots, consider exploring our comprehensive guides to <b><i><a href=\"https://explorenationalparks.store/girls-sneakers\" style=\"color: #3b82f6;\">girls sneakers</a></i></b> for dry weather activities, <b><i><a href=\"https://explorenationalparks.store/girls-winter-boots\" style=\"color: #3b82f6;\">girls winter boots</a></i></b> for cold weather protection, or <b><i><a href=\"https://explorenationalparks.store/girls-ankle-boots\" style=\"color: #3b82f6;\">girls ankle boots</a></i></b> for transitional seasons. Each footwear category serves specific needs and conditions that complement wellington boots in a well-rounded shoe wardrobe.</p>\n</section>\n\n<section id=\"conclusion\" style=\"margin-bottom: 50px;\">\n<h2 style=\"font-size: 2rem; font-weight: bold; color: #1f2937; margin-bottom: 25px; border-bottom: 3px solid #3b82f6; padding-bottom: 10px;\">Conclusion</h2>\n\n<p style=\"margin-bottom: 20px; font-size: 1.1rem;\">Choosing the right girls wellies transforms rainy days from indoor confinement into outdoor adventure opportunities. Through extensive testing with my own daughters and research across dozens of brands, I've learned that the perfect wellington boots balance quality construction, proper fit, and designs that spark enthusiasm for outdoor exploration. The investment in quality girls wellies pays dividends through years of reliable service, enhanced outdoor confidence, and countless memories made in all weather conditions.</p>\n\n<p style=\"margin-bottom: 20px; font-size: 1.1rem;\">Remember that girls wellies serve as more than just waterproof footwear—they're tools for independence, confidence-building, and connection with nature. Whether you choose premium brands like Hunter for long-term durability, character-themed options to encourage reluctant wearers, or mid-range selections that balance performance with budget considerations, the right wellington boots will serve your daughter well through years of puddle jumping, trail hiking, and outdoor adventures.</p>\n\n<div style=\"background: #dbeafe; padding: 25px; border-radius: 10px; margin: 25px 0; text-align: center;\">\n<h4 style=\"font-size: 1.2rem; font-weight: bold; margin-bottom: 15px; color: #1e40af;\">🌟 Best Overall Value</h4>\n<a href=\"https://www.amazon.com/dp/B0DPL1MF1P?tag=natureguests00-20\" style=\"text-decoration: none;\">\n<div style=\"border: 2px solid #3b82f6; padding: 20px; border-radius: 10px; background: white;\">\n<h5 style=\"color: #1e40af; margin-bottom: 10px; font-weight: bold;\">Minnie Mouse Girls Wellington Boots</h5>\n<p style=\"color: #374151; margin-bottom: 15px;\">Handle wellies with Minnie &amp; Daisy character print in beige and pink. Perfect combination of fun design and practical functionality.</p>\n<button style=\"background: linear-gradient(135deg, #667eea 0%, #764ba2 100%); color: white; padding: 12px 24px; border: none; border-radius: 25px; font-weight: bold; cursor: pointer; font-size: 1rem;\">Shop Minnie Mouse Wellies</button>\n</div>\n</a>\n</div>\n\n<p style=\"margin-bottom: 20px; font-size: 1.1rem;\">The key to successful girls wellies selection lies in understanding your daughter's specific needs, activity level, and preferences while balancing quality with budget considerations. Use this guide as your foundation, but remember that the best wellington boots are those that encourage your daughter to embrace outdoor adventures with enthusiasm and confidence. For additional footwear guidance, explore our related articles on <b><i><a href=\"https://explorenationalparks.store/girls-school-shoes\" style=\"color: #3b82f6;\">girls school shoes</a></i></b>, <b><i><a href=\"https://explorenationalparks.store/girls-sandals\" style=\"color: #3b82f6;\">girls sandals</a></i></b>, and comprehensive <b><i><a href=\"https://explorenationalparks.store/girls-shoes\" style=\"color: #3b82f6;\">girls shoes</a></i></b> selection guides.</p>\n\n<div style=\"background: linear-gradient(135deg, #667eea 0%, #764ba2 100%); color: white; padding: 30px; border-radius: 15px; margin: 30px 0; text-align: center;\">\n<h3 style=\"margin-bottom: 15px; font-size: 1.5rem;\">Ready to Find the Perfect Girls Wellies?</h3>\n<p style=\"margin-bottom: 20px; font-size: 1.1rem;\">Start your outdoor adventure journey with confidence! Visit our homepage for more expert gear recommendations and guides.</p>\n<a href=\"https://explorenationalparks.store/\" style=\"background: #fbbf24; color: #92400e; padding: 15px 30px; border-radius: 25px; text-decoration: none; font-weight: bold; font-size: 1.1rem; display: inline-block;\">Explore More Outdoor Gear Guides</a>\n</div>\n</section>\n\n<section id=\"faq\" style=\"margin-bottom: 50px;\">\n<h2 style=\"font-size: 2rem; font-weight: bold; color: #1f2937; margin-bottom: 25px; border-bottom: 3px solid #3b82f6; padding-bottom: 10px;\">Frequently Asked Questions</h2>\n\n<div style=\"background: #f9fafb; padding: 25px; border-radius: 10px; margin-bottom: 25px;\">\n<h3 style=\"font-size: 1.3rem; font-weight: bold; color: #1f2937; margin-bottom: 15px;\">What age should girls start wearing wellington boots?</h3>\n<p style=\"margin-bottom: 0; font-size: 1.1rem; line-height: 1.7;\">Girls can start wearing wellington boots as early as 12-18 months when they begin walking confidently. At this age, toddler-specific wellies with easy-on handles and flexible soles are ideal. Many parents find that once their daughter reaches 2-3 years old, she can manage putting on wellies independently with minimal assistance. The key is choosing age-appropriate designs with features like wider openings, shorter heights, and lightweight materials that won't overwhelm small feet or make walking difficult. Consider complementing wellies with other <b><i><a href=\"https://explorenationalparks.store/kids-boots-girls\" style=\"color: #3b82f6;\">kids boots for girls</a></i></b> as your child grows.</p>\n</div>\n\n<div style=\"background: #f9fafb; padding: 25px; border-radius: 10px; margin-bottom: 25px;\">\n<h3 style=\"font-size: 1.3rem; font-weight: bold; color: #1f2937; margin-bottom: 15px;\">How do I choose the right size girls wellies?</h3>\n<p style=\"margin-bottom: 0; font-size: 1.1rem; line-height: 1.7;\">Choosing the right size girls wellies requires measuring both feet and allowing for growth room. Wellies should have 0.5-1 inch of space between the longest toe and boot front. Measure feet in the afternoon when they're naturally slightly swollen for the most accurate fit. Consider the thickness of socks she'll wear - winter wellies need room for thick socks while summer wellies work with thinner socks. Most quality brands run true to size, but always check specific sizing charts as some European brands may differ from US sizing standards. Remember that proper fit is crucial for comfort during extended wear.</p>\n</div>\n\n<div style=\"background: #f9fafb; padding: 25px; border-radius: 10px; margin-bottom: 25px;\">\n<h3 style=\"font-size: 1.3rem; font-weight: bold; color: #1f2937; margin-bottom: 15px;\">Are expensive girls wellies worth the investment?</h3>\n<p style=\"margin-bottom: 0; font-size: 1.1rem; line-height: 1.7;\">Expensive girls wellies are often worth the investment for active families. Premium brands like Hunter, Joules, and Aigle offer superior waterproofing, durability, and comfort features that justify higher prices. Quality wellies last 2-3 years with proper care, while cheaper alternatives may crack or lose waterproofing within months. However, if your daughter only wears wellies occasionally or outgrows shoes quickly, mid-range options from brands like Next or Trespass provide excellent value. Consider your specific needs, usage frequency, and budget when deciding on investment level. Factor in the cost per wear over the boot's lifespan for true value assessment.</p>\n</div>\n\n<div style=\"background: #f9fafb; padding: 25px; border-radius: 10px; margin-bottom: 25px;\">\n<h3 style=\"font-size: 1.3rem; font-weight: bold; color: #1f2937; margin-bottom: 15px;\">How do I clean and maintain girls wellies?</h3>\n<p style=\"margin-bottom: 0; font-size: 1.1rem; line-height: 1.7;\">Cleaning girls wellies properly extends their lifespan significantly. After each use, rinse off mud and debris with cold water, using a soft brush for stubborn dirt. For deep cleaning, use mild soap and warm water, avoiding harsh chemicals that can damage rubber. Allow wellies to air dry naturally away from direct heat sources like radiators, which can cause cracking. Store in a cool, dry place and periodically apply rubber conditioner to maintain flexibility. Check regularly for small cracks or holes and repair promptly with rubber cement to prevent water penetration. Proper maintenance can double the usable life of quality wellington boots.</p>\n</div>\n\n<div style=\"background: #f9fafb; padding: 25px; border-radius: 10px; margin-bottom: 25px;\">\n<h3 style=\"font-size: 1.3rem; font-weight: bold; color: #1f2937; margin-bottom: 15px;\">What's the difference between rain boots and wellington boots?</h3>\n<p style=\"margin-bottom: 0; font-size: 1.1rem; line-height: 1.7;\">Rain boots and wellington boots are essentially the same product with regional naming differences. 'Wellington boots' or 'wellies' is the traditional British term, while 'rain boots' is more commonly used in North America. Both refer to waterproof, knee-high or mid-calf boots made from rubber or synthetic materials. The original Wellington boot was invented in the early 1800s and named after the Duke of Wellington. Today's girls wellies maintain the same basic design principles while incorporating modern materials and colorful, fun designs that appeal to children. Some manufacturers may use slightly different constructions, but functionally they serve identical purposes for weather protection and outdoor activities.</p>\n</div>\n\n<div style=\"background: #f9fafb; padding: 25px; border-radius: 10px; margin-bottom: 25px;\">\n<h3 style=\"font-size: 1.3rem; font-weight: bold; color: #1f2937; margin-bottom: 15px;\">Can girls wear wellies in snow?</h3>\n<p style=\"margin-bottom: 0; font-size: 1.1rem; line-height: 1.7;\">Girls can wear wellies in light snow conditions, but they're not ideal for deep snow or extremely cold temperatures. Standard wellies lack insulation and traction needed for serious winter conditions. For snowy weather, look for insulated or neoprene-lined wellies with deeper tread patterns. However, dedicated <b><i><a href=\"https://explorenationalparks.store/girls-snow-boots\" style=\"color: #3b82f6;\">girls snow boots</a></i></b> offer superior warmth, insulation, and grip for extended outdoor play in snow. If using wellies in snow, pair them with thick wool socks and limit exposure time. Consider our comprehensive guide to winter footwear options for better cold-weather alternatives that provide the specialized features needed for snowy conditions and freezing temperatures.</p>\n</div>\n</section></article>\n\n<footer style=\"background: #1f2937; color: white; padding: 30px; border-radius: 10px; margin-top: 50px; text-align: center;\">\n<p style=\"margin: 0; font-size: 0.9rem;\">© 2025 Explore National Parks Store. Expert outdoor gear guides for adventurous families. <a href=\"https://explorenationalparks.store/\" style=\"color: #fbbf24; text-decoration: none;\">Visit our homepage</a> for more comprehensive guides.</p>\n<p style=\"margin: 10px 0 0 0; font-size: 0.8rem; opacity: 0.8;\">Disclosure: This article contains affiliate links. We may earn a commission from purchases made through these links at no additional cost to you. Our recommendations are based on thorough research and real-world testing to help you make informed decisions for your family's outdoor adventures.</p>\n</footer>\n\n<script defer=\"\" src=\"https://static.cloudflareinsights.com/beacon.min.js/vcd15cbe7772f49c399c6a5babf22c1241717689176015\" integrity=\"sha512-ZpsOmlRQV6y907TI0dKBHq9Md29nnaEIPlkf84rnaERnq6zvWvPUqr2ft8M1aS28oN72PdrCzSjY4U6VaAw1EQ==\" data-cf-beacon=\"{&quot;rayId&quot;:&quot;96cc8b497db340d2&quot;,&quot;serverTiming&quot;:{&quot;name&quot;:{&quot;cfExtPri&quot;:true,&quot;cfEdge&quot;:true,&quot;cfOrigin&quot;:true,&quot;cfL4&quot;:true,&quot;cfSpeedBrain&quot;:true,&quot;cfCacheStatus&quot;:true}},&quot;version&quot;:&quot;2025.7.0&quot;,&quot;token&quot;:&quot;4edd5f8ec12a48cfa682ab8261b80a79&quot;}\" crossorigin=\"anonymous\"></script>\n\n    <script id=\"html_badge_script1\">\n        window.__genspark_remove_badge_link = \"https://www.genspark.ai/api/html_badge/\" +\n            \"remove_badge?token=To%2FBnjzloZ3UfQdcSaYfDvn%2FZwrhnUjucdFQMxHA3zmSBw5ssK6EtW7DwhKnPVzrw5bpL3AWYUvQVS6wxiJcH%2FERlc5PSRnxUWrr8DOekcmt%2BeaMECyGfBKYb52nK0Bc0JpIApty5Hfde5b4w9Bc%2B7Cg%2BZaCiop%2Fah9r33trFeIdRcBynvlV%2B5eKD2YvqT%2F8Cmi%2FDoZfyOwzMs5bP8322EBPFpieJcNqKeBybDOKyxwtynsIuje%2F16pEUBab%2FrDZMtuJSvLveFQvqfvuHffH%2BvY4YRxM%2FcVi0nNL2AwvZ%2FRcq2q4vcrYz%2F4e%2BXZMKIrjqpOAAppEzqVXiQlFJ6bixX2JqR9QmB3Y2uvwou%2FRFFMTyHasAFtFUHyu7v2bIvpNou4QMuQRdDPiPwIwI%2F9%2FjGgf5eHuOVqI6wNPGuOk0RhKwH%2FrhWO4R7H7bq7HnN8rEe7LcAGQuHKwWo2i1A1U9m083jOK3ALcx3dZaRciWvPOjapt3h7dSCS6oHZYMMAaCyAEiNF9pbW5Isn3yhhQoww2SN0w83tsQuyaLMNl%2BWc%3D\";\n        window.__genspark_locale = \"en-US\";\n        window.__genspark_token = \"To/BnjzloZ3UfQdcSaYfDvn/ZwrhnUjucdFQMxHA3zmSBw5ssK6EtW7DwhKnPVzrw5bpL3AWYUvQVS6wxiJcH/ERlc5PSRnxUWrr8DOekcmt+eaMECyGfBKYb52nK0Bc0JpIApty5Hfde5b4w9Bc+7Cg+ZaCiop/ah9r33trFeIdRcBynvlV+5eKD2YvqT/8Cmi/DoZfyOwzMs5bP8322EBPFpieJcNqKeBybDOKyxwtynsIuje/16pEUBab/rDZMtuJSvLveFQvqfvuHffH+vY4YRxM/cVi0nNL2AwvZ/Rcq2q4vcrYz/4e+XZMKIrjqpOAAppEzqVXiQlFJ6bixX2JqR9QmB3Y2uvwou/RFFMTyHasAFtFUHyu7v2bIvpNou4QMuQRdDPiPwIwI/9/jGgf5eHuOVqI6wNPGuOk0RhKwH/rhWO4R7H7bq7HnN8rEe7LcAGQuHKwWo2i1A1U9m083jOK3ALcx3dZaRciWvPOjapt3h7dSCS6oHZYMMAaCyAEiNF9pbW5Isn3yhhQoww2SN0w83tsQuyaLMNl+Wc=\";\n    </script>\n    \n        <script id=\"html_badge_script2\" src=\"https://www.genspark.ai/html_badge.js\"></script><button class=\"genspark-badge-button\"><svg xmlns=\"http://www.w3.org/2000/svg\" width=\"14\" height=\"14\" viewBox=\"0 0 14 14\" fill=\"none\">\n<path d=\"M11.3412 0H2.65879C1.19038 0 0 1.19038 0 2.65879V11.3412C0 12.8096 1.19038 14 2.65879 14H11.3412C12.8096 14 14 12.8096 14 11.3412V2.65879C14 1.19038 12.8096 0 11.3412 0Z\" fill=\"white\"></path>\n<path d=\"M11.7403 10.7031H2.29243C2.09641 10.7031 1.9375 10.862 1.9375 11.0581V11.8033C1.9375 11.9993 2.09641 12.1582 2.29243 12.1582H11.7403C11.9363 12.1582 12.0952 11.9993 12.0952 11.8033V11.0581C12.0952 10.862 11.9363 10.7031 11.7403 10.7031Z\" fill=\"#232425\"></path>\n<path d=\"M5.09178 9.18166C5.03494 9.18166 4.98695 9.13998 4.97811 9.08314C4.60803 6.63655 4.34025 6.42056 1.91134 6.05427C1.83682 6.0429 1.78125 5.97848 1.78125 5.9027C1.78125 5.82691 1.83682 5.7625 1.91134 5.75113C4.32762 5.3861 4.54235 5.17011 4.90738 2.7551C4.91874 2.68058 4.98316 2.625 5.05894 2.625C5.13473 2.625 5.19914 2.68058 5.21051 2.7551C5.57554 5.17011 5.79153 5.3861 8.20655 5.75113C8.28107 5.7625 8.33664 5.82691 8.33664 5.9027C8.33664 5.97848 8.28107 6.0429 8.20655 6.05427C5.78017 6.42056 5.57302 6.63655 5.20546 9.08314C5.19662 9.13871 5.14862 9.18166 5.09178 9.18166Z\" fill=\"#232425\"></path>\n<path d=\"M9.70174 5.949C9.66637 5.949 9.63606 5.92248 9.63101 5.88711C9.39986 4.35878 9.23188 4.22363 7.71492 3.99501C7.66818 3.98743 7.63281 3.94828 7.63281 3.90028C7.63281 3.85355 7.66692 3.81313 7.71492 3.80555C9.2243 3.5782 9.35945 3.44305 9.5868 1.93366C9.59438 1.88693 9.63354 1.85156 9.68153 1.85156C9.72827 1.85156 9.76869 1.88567 9.77627 1.93366C10.0036 3.44305 10.1388 3.5782 11.6482 3.80555C11.6949 3.81313 11.7302 3.85228 11.7302 3.90028C11.7302 3.94702 11.6962 3.98743 11.6482 3.99501C10.1325 4.22363 10.0024 4.35878 9.77247 5.88711C9.76742 5.92248 9.73711 5.949 9.70174 5.949Z\" fill=\"#232425\"></path>\n<path d=\"M9.69114 9.76325C9.6684 9.76325 9.64946 9.74683 9.64567 9.7241C9.49915 8.75152 9.39179 8.66563 8.42679 8.52038C8.39648 8.51533 8.375 8.49007 8.375 8.45975C8.375 8.42944 8.39648 8.40418 8.42679 8.39912C9.38673 8.25387 9.47262 8.16798 9.61788 7.20804C9.62293 7.17772 9.64819 7.15625 9.6785 7.15625C9.70882 7.15625 9.73408 7.17772 9.73913 7.20804C9.88439 8.16798 9.97028 8.25387 10.9302 8.39912C10.9605 8.40418 10.982 8.42944 10.982 8.45975C10.982 8.49007 10.9605 8.51533 10.9302 8.52038C9.96523 8.66563 9.88312 8.75152 9.73661 9.7241C9.73282 9.74683 9.71387 9.76325 9.69114 9.76325Z\" fill=\"#232425\"></path>\n</svg> Made with Genspark</button><div class=\"genspark-modal\">\n    <div class=\"genspark-modal-content\">\n      <button class=\"genspark-close\"><svg xmlns=\"http://www.w3.org/2000/svg\" width=\"14\" height=\"14\" viewBox=\"0 0 14 14\" fill=\"none\">\n<path d=\"M11 3L3 11M3 3L11 11\" stroke=\"#232425\" stroke-linecap=\"round\" stroke-linejoin=\"round\"></path>\n</svg></button>\n      <h3 class=\"genspark-title\">This page was created by users with AI.</h3>\n      <a class=\"genspark-report\" href=\"mailto:support@genspark.ai?subject=Report%20inappropriate%20content&amp;body=Current%20URL:%20https://www.genspark.ai/api/page_private?id=tlnrkxsn\">Report inappropriate content.</a>\n      <p class=\"genspark-info\">Page owner with Plus Plan can remove badge.</p>\n      <div class=\"genspark-buttons\">\n        <button class=\"genspark-remove-btn\">Remove Badge</button>\n        <button class=\"genspark-go-btn\">Go to Genspark</button>\n      </div>\n    </div>\n  </div>\n        \n    <script id=\"html_notice_dialog_script\" src=\"https://www.genspark.ai/notice_dialog.js\"></script>\n    "
}